{
  "project_info": {
    "project_number": "367709543112",
    "project_id": "mapp-f9764",
    "storage_bucket": "mapp-f9764.appspot.com"
  },
  "client": [
    {
      "client_info": {
        "mobilesdk_app_id": "1:367709543112:android:a9960459e3c3bbd40b63fd",
        "android_client_info": {
          "package_name": "com.example.mapp"
        }
      },
      "oauth_client": [
        {
          "client_id": "367709543112-gob6m9f9bokijt2ilrnfo2t6hbvonm9v.apps.googleusercontent.com",
          "client_type": 3
        }
      ],
      "api_key": [
        {
          "current_key": "AIzaSyBGXAPK_wGXSutNC_0QOmJGrvjQZgo6Zm8"
        }
      ],
      "services": {
        "appinvite_service": {
          "other_platform_oauth_client": [
            {
              "client_id": "367709543112-gob6m9f9bokijt2ilrnfo2t6hbvonm9v.apps.googleusercontent.com",
              "client_type": 3
            }
          ]
        }
      }
    }
  ],
  "configuration_version": "1"
}